odoo/addons/stock_picking_progress/README.rst
odoo/addons/stock_picking_progress/__init__.py
odoo/addons/stock_picking_progress/__manifest__.py
odoo/addons/stock_picking_progress/hooks.py
odoo/addons/stock_picking_progress/i18n/it.po
odoo/addons/stock_picking_progress/i18n/pt.po
odoo/addons/stock_picking_progress/i18n/pt_BR.po
odoo/addons/stock_picking_progress/i18n/stock_picking_progress.pot
odoo/addons/stock_picking_progress/models/__init__.py
odoo/addons/stock_picking_progress/models/stock_move.py
odoo/addons/stock_picking_progress/models/stock_picking.py
odoo/addons/stock_picking_progress/readme/CONTRIBUTORS.md
odoo/addons/stock_picking_progress/readme/CREDITS.md
odoo/addons/stock_picking_progress/readme/DESCRIPTION.md
odoo/addons/stock_picking_progress/static/description/icon.png
odoo/addons/stock_picking_progress/static/description/index.html
odoo/addons/stock_picking_progress/tests/__init__.py
odoo/addons/stock_picking_progress/tests/test_progress.py
odoo/addons/stock_picking_progress/views/stock_picking.xml
odoo_addon_stock_picking_progress-18.0.1.0.1.dist-info/METADATA
odoo_addon_stock_picking_progress-18.0.1.0.1.dist-info/WHEEL
odoo_addon_stock_picking_progress-18.0.1.0.1.dist-info/top_level.txt
odoo_addon_stock_picking_progress-18.0.1.0.1.dist-info/RECORD
